x17_container/__init__.py
x17_lib_container-0.1.2.dist-info/METADATA
x17_lib_container-0.1.2.dist-info/WHEEL
x17_lib_container-0.1.2.dist-info/top_level.txt
x17_lib_container-0.1.2.dist-info/RECORD
