Metadata-Version: 2.4
Name: x17-lib-container
Version: 0.1.2
Author-email: Xing Xing <x.xing.work@gmail.com>
License: MIT
Requires-Python: >=3.10
Requires-Dist: build
Requires-Dist: docker
Requires-Dist: x17-lib-base
